captn/__init__.py
captn/_modidx.py
captn/client.py
captn/_cli/__init__.py
captn/_cli/api_key.py
captn/_cli/cli.py
captn/_cli/db.py
captn/_cli/ds.py
captn/_cli/token.py
captn/_cli/user.py
captn/_cli/version.py
captn/_testing/__init__.py
captn/_testing/activate_by_import.py
captn_client-2023.3.0.dist-info/LICENSE
captn_client-2023.3.0.dist-info/METADATA
captn_client-2023.3.0.dist-info/WHEEL
captn_client-2023.3.0.dist-info/entry_points.txt
captn_client-2023.3.0.dist-info/top_level.txt
captn_client-2023.3.0.dist-info/RECORD
